{
  "kind": "collectionType",
  "collectionName": "flashsaleproducts",
  "info": {
    "name": "Flashsaleproducts"
  },
  "options": {
    "increments": true,
    "timestamps": true
  },
  "attributes": {
    "flashsale": {
      "model": "flashsale"
    },
    "flashsoldqtty": {
      "type": "decimal"
    },
    "remark": {
      "type": "string"
    },
    "products": {
      "via": "flashsaleproduct",
      "collection": "product"
    },
    "flashsaletype": {
      "type": "integer"
    },
    "reduction": {
      "type": "float"
    },
    "flashsaleapplytype": {
      "type": "integer"
    },
    "flashsaleapplyfor": {
      "type": "integer"
    },
    "minimumorderqtty": {
      "type": "integer"
    },
    "maximumorderqtty": {
      "type": "integer"
    },
    "numberapply": {
      "type": "integer"
    },
    "name": {
      "type": "string"
    }
  }
}
